{"taxonID": "0-0-0", "level": 0, "path": "root", "name": "root", "keywords": ["computer_science"], "children": [{"taxonID": "1-1-1", "level": "1", "path": "undergarment", "keywords": ["nouse"], "name": "undergarment", "children": [{"taxonID": "1-1-1", "level": "1", "path": "undergarment/underwear", "keywords": ["nouse"], "name": "underwear", "children": [{"taxonID": "1-1-1", "level": "1", "path": "undergarment/underwear/BVD", "keywords": ["nouse"], "name": "BVD"}, {"taxonID": "1-1-1", "level": "1", "path": "undergarment/underwear/long_$_johns", "keywords": ["nouse"], "name": "long_$_johns"}, {"taxonID": "1-1-1", "level": "1", "path": "undergarment/underwear/Skivvies", "keywords": ["nouse"], "name": "Skivvies"}, {"taxonID": "1-1-1", "level": "1", "path": "undergarment/underwear/lingerie", "keywords": ["nouse"], "name": "lingerie", "children": [{"taxonID": "1-1-1", "level": "1", "path": "undergarment/underwear/lingerie/nightgown", "keywords": ["nouse"], "name": "nightgown"}, {"taxonID": "1-1-1", "level": "1", "path": "undergarment/underwear/lingerie/undies", "keywords": ["nouse"], "name": "undies"}]}]}, {"taxonID": "1-1-1", "level": "1", "path": "undergarment/camisole", "keywords": ["nouse"], "name": "camisole"}, {"taxonID": "1-1-1", "level": "1", "path": "undergarment/petticoat", "keywords": ["nouse"], "name": "petticoat", "children": [{"taxonID": "1-1-1", "level": "1", "path": "undergarment/petticoat/crinoline", "keywords": ["nouse"], "name": "crinoline"}]}, {"taxonID": "1-1-1", "level": "1", "path": "undergarment/garter_$_belt", "keywords": ["nouse"], "name": "garter_$_belt"}, {"taxonID": "1-1-1", "level": "1", "path": "undergarment/body_$_stocking", "keywords": ["nouse"], "name": "body_$_stocking"}, {"taxonID": "1-1-1", "level": "1", "path": "undergarment/underpants", "keywords": ["nouse"], "name": "underpants", "children": [{"taxonID": "1-1-1", "level": "1", "path": "undergarment/underpants/bikini_$_pants", "keywords": ["nouse"], "name": "bikini_$_pants"}, {"taxonID": "1-1-1", "level": "1", "path": "undergarment/underpants/drawers", "keywords": ["nouse"], "name": "drawers"}, {"taxonID": "1-1-1", "level": "1", "path": "undergarment/underpants/briefs", "keywords": ["nouse"], "name": "briefs"}, {"taxonID": "1-1-1", "level": "1", "path": "undergarment/underpants/pantie", "keywords": ["nouse"], "name": "pantie"}, {"taxonID": "1-1-1", "level": "1", "path": "undergarment/underpants/thong", "keywords": ["nouse"], "name": "thong"}, {"taxonID": "1-1-1", "level": "1", "path": "undergarment/underpants/bloomers", "keywords": ["nouse"], "name": "bloomers"}]}, {"taxonID": "1-1-1", "level": "1", "path": "undergarment/chemise", "keywords": ["nouse"], "name": "chemise"}, {"taxonID": "1-1-1", "level": "1", "path": "undergarment/long_$_underwear", "keywords": ["nouse"], "name": "long_$_underwear"}, {"taxonID": "1-1-1", "level": "1", "path": "undergarment/foundation_$_garment", "keywords": ["nouse"], "name": "foundation_$_garment", "children": [{"taxonID": "1-1-1", "level": "1", "path": "undergarment/foundation_$_garment/corset", "keywords": ["nouse"], "name": "corset", "children": [{"taxonID": "1-1-1", "level": "1", "path": "undergarment/foundation_$_garment/corset/panty_$_girdle", "keywords": ["nouse"], "name": "panty_$_girdle"}]}, {"taxonID": "1-1-1", "level": "1", "path": "undergarment/foundation_$_garment/roll-on", "keywords": ["nouse"], "name": "roll-on"}]}, {"taxonID": "1-1-1", "level": "1", "path": "undergarment/brassiere", "keywords": ["nouse"], "name": "brassiere", "children": [{"taxonID": "1-1-1", "level": "1", "path": "undergarment/brassiere/uplift", "keywords": ["nouse"], "name": "uplift"}]}, {"taxonID": "1-1-1", "level": "1", "path": "undergarment/singlet", "keywords": ["nouse"], "name": "singlet"}]}]}