{"taxonID": "0-0-0", "level": 0, "path": "root", "name": "root", "keywords": ["computer_science"], "children": [{"taxonID": "1-1-1", "level": "1", "path": "football_$_player", "keywords": ["nouse"], "name": "football_$_player", "children": [{"taxonID": "1-1-1", "level": "1", "path": "football_$_player/ball_$_carrier", "keywords": ["nouse"], "name": "ball_$_carrier", "children": [{"taxonID": "1-1-1", "level": "1", "path": "football_$_player/ball_$_carrier/rusher", "keywords": ["nouse"], "name": "rusher"}, {"taxonID": "1-1-1", "level": "1", "path": "football_$_player/ball_$_carrier/passer", "keywords": ["nouse"], "name": "passer"}]}, {"taxonID": "1-1-1", "level": "1", "path": "football_$_player/tackler", "keywords": ["nouse"], "name": "tackler"}, {"taxonID": "1-1-1", "level": "1", "path": "football_$_player/football_$_hero", "keywords": ["nouse"], "name": "football_$_hero"}, {"taxonID": "1-1-1", "level": "1", "path": "football_$_player/linebacker", "keywords": ["nouse"], "name": "linebacker"}, {"taxonID": "1-1-1", "level": "1", "path": "football_$_player/back", "keywords": ["nouse"], "name": "back", "children": [{"taxonID": "1-1-1", "level": "1", "path": "football_$_player/back/quarterback", "keywords": ["nouse"], "name": "quarterback"}, {"taxonID": "1-1-1", "level": "1", "path": "football_$_player/back/wingback", "keywords": ["nouse"], "name": "wingback"}, {"taxonID": "1-1-1", "level": "1", "path": "football_$_player/back/flanker_$_back", "keywords": ["nouse"], "name": "flanker_$_back"}, {"taxonID": "1-1-1", "level": "1", "path": "football_$_player/back/running_$_back", "keywords": ["nouse"], "name": "running_$_back", "children": [{"taxonID": "1-1-1", "level": "1", "path": "football_$_player/back/running_$_back/fullback", "keywords": ["nouse"], "name": "fullback"}, {"taxonID": "1-1-1", "level": "1", "path": "football_$_player/back/running_$_back/halfback", "keywords": ["nouse"], "name": "halfback"}]}, {"taxonID": "1-1-1", "level": "1", "path": "football_$_player/back/tailback", "keywords": ["nouse"], "name": "tailback"}]}, {"taxonID": "1-1-1", "level": "1", "path": "football_$_player/kicker", "keywords": ["nouse"], "name": "kicker", "children": [{"taxonID": "1-1-1", "level": "1", "path": "football_$_player/kicker/place-kicker", "keywords": ["nouse"], "name": "place-kicker"}, {"taxonID": "1-1-1", "level": "1", "path": "football_$_player/kicker/dropkicker", "keywords": ["nouse"], "name": "dropkicker"}, {"taxonID": "1-1-1", "level": "1", "path": "football_$_player/kicker/punter", "keywords": ["nouse"], "name": "punter"}]}, {"taxonID": "1-1-1", "level": "1", "path": "football_$_player/blocker", "keywords": ["nouse"], "name": "blocker"}, {"taxonID": "1-1-1", "level": "1", "path": "football_$_player/cornerback", "keywords": ["nouse"], "name": "cornerback"}, {"taxonID": "1-1-1", "level": "1", "path": "football_$_player/receiver", "keywords": ["nouse"], "name": "receiver"}, {"taxonID": "1-1-1", "level": "1", "path": "football_$_player/lineman", "keywords": ["nouse"], "name": "lineman", "children": [{"taxonID": "1-1-1", "level": "1", "path": "football_$_player/lineman/center", "keywords": ["nouse"], "name": "center"}, {"taxonID": "1-1-1", "level": "1", "path": "football_$_player/lineman/guard", "keywords": ["nouse"], "name": "guard"}, {"taxonID": "1-1-1", "level": "1", "path": "football_$_player/lineman/tackle", "keywords": ["nouse"], "name": "tackle"}, {"taxonID": "1-1-1", "level": "1", "path": "football_$_player/lineman/end", "keywords": ["nouse"], "name": "end", "children": [{"taxonID": "1-1-1", "level": "1", "path": "football_$_player/lineman/end/tight_$_end", "keywords": ["nouse"], "name": "tight_$_end"}, {"taxonID": "1-1-1", "level": "1", "path": "football_$_player/lineman/end/split_$_end", "keywords": ["nouse"], "name": "split_$_end"}]}]}]}]}