{"taxonID": "0-0-0", "level": 0, "path": "root", "name": "root", "keywords": ["computer_science"], "children": [{"taxonID": "1-1-1", "level": "1", "path": "saurischian", "keywords": ["nouse"], "name": "saurischian", "children": [{"taxonID": "1-1-1", "level": "1", "path": "saurischian/sauropod", "keywords": ["nouse"], "name": "sauropod", "children": [{"taxonID": "1-1-1", "level": "1", "path": "saurischian/sauropod/apatosaur", "keywords": ["nouse"], "name": "apatosaur"}, {"taxonID": "1-1-1", "level": "1", "path": "saurischian/sauropod/barosaur", "keywords": ["nouse"], "name": "barosaur"}]}, {"taxonID": "1-1-1", "level": "1", "path": "saurischian/theropod", "keywords": ["nouse"], "name": "theropod", "children": [{"taxonID": "1-1-1", "level": "1", "path": "saurischian/theropod/ceratosaur", "keywords": ["nouse"], "name": "ceratosaur", "children": [{"taxonID": "1-1-1", "level": "1", "path": "saurischian/theropod/ceratosaur/coelophysis", "keywords": ["nouse"], "name": "coelophysis"}]}, {"taxonID": "1-1-1", "level": "1", "path": "saurischian/theropod/carnosaur", "keywords": ["nouse"], "name": "carnosaur"}, {"taxonID": "1-1-1", "level": "1", "path": "saurischian/theropod/eoraptor", "keywords": ["nouse"], "name": "eoraptor"}, {"taxonID": "1-1-1", "level": "1", "path": "saurischian/theropod/tyrannosaur", "keywords": ["nouse"], "name": "tyrannosaur"}, {"taxonID": "1-1-1", "level": "1", "path": "saurischian/theropod/herrerasaur", "keywords": ["nouse"], "name": "herrerasaur"}, {"taxonID": "1-1-1", "level": "1", "path": "saurischian/theropod/maniraptor", "keywords": ["nouse"], "name": "maniraptor", "children": [{"taxonID": "1-1-1", "level": "1", "path": "saurischian/theropod/maniraptor/deinonychus", "keywords": ["nouse"], "name": "deinonychus"}, {"taxonID": "1-1-1", "level": "1", "path": "saurischian/theropod/maniraptor/velociraptor", "keywords": ["nouse"], "name": "velociraptor"}, {"taxonID": "1-1-1", "level": "1", "path": "saurischian/theropod/maniraptor/Mononychus_$_olecranus", "keywords": ["nouse"], "name": "Mononychus_$_olecranus"}, {"taxonID": "1-1-1", "level": "1", "path": "saurischian/theropod/maniraptor/dromaeosaur", "keywords": ["nouse"], "name": "dromaeosaur"}, {"taxonID": "1-1-1", "level": "1", "path": "saurischian/theropod/maniraptor/oviraptorid", "keywords": ["nouse"], "name": "oviraptorid"}, {"taxonID": "1-1-1", "level": "1", "path": "saurischian/theropod/maniraptor/utahraptor", "keywords": ["nouse"], "name": "utahraptor"}]}, {"taxonID": "1-1-1", "level": "1", "path": "saurischian/theropod/compsognathus", "keywords": ["nouse"], "name": "compsognathus"}, {"taxonID": "1-1-1", "level": "1", "path": "saurischian/theropod/allosaur", "keywords": ["nouse"], "name": "allosaur"}, {"taxonID": "1-1-1", "level": "1", "path": "saurischian/theropod/ornithomimid", "keywords": ["nouse"], "name": "ornithomimid", "children": [{"taxonID": "1-1-1", "level": "1", "path": "saurischian/theropod/ornithomimid/struthiomimus", "keywords": ["nouse"], "name": "struthiomimus"}, {"taxonID": "1-1-1", "level": "1", "path": "saurischian/theropod/ornithomimid/deinocheirus", "keywords": ["nouse"], "name": "deinocheirus"}]}, {"taxonID": "1-1-1", "level": "1", "path": "saurischian/theropod/megalosaur", "keywords": ["nouse"], "name": "megalosaur"}]}]}]}