{"taxonID": "0-0-0", "level": 0, "path": "root", "name": "root", "keywords": ["computer_science"], "children": [{"taxonID": "1-1-1", "level": "1", "path": "manner_$_of_$_speaking", "keywords": ["nouse"], "name": "manner_$_of_$_speaking", "children": [{"taxonID": "1-1-1", "level": "1", "path": "manner_$_of_$_speaking/prosody", "keywords": ["nouse"], "name": "prosody", "children": [{"taxonID": "1-1-1", "level": "1", "path": "manner_$_of_$_speaking/prosody/stress", "keywords": ["nouse"], "name": "stress", "children": [{"taxonID": "1-1-1", "level": "1", "path": "manner_$_of_$_speaking/prosody/stress/word_$_stress", "keywords": ["nouse"], "name": "word_$_stress"}, {"taxonID": "1-1-1", "level": "1", "path": "manner_$_of_$_speaking/prosody/stress/tonic_$_accent", "keywords": ["nouse"], "name": "tonic_$_accent"}, {"taxonID": "1-1-1", "level": "1", "path": "manner_$_of_$_speaking/prosody/stress/accentuation", "keywords": ["nouse"], "name": "accentuation"}, {"taxonID": "1-1-1", "level": "1", "path": "manner_$_of_$_speaking/prosody/stress/sentence_$_stress", "keywords": ["nouse"], "name": "sentence_$_stress"}]}, {"taxonID": "1-1-1", "level": "1", "path": "manner_$_of_$_speaking/prosody/intonation", "keywords": ["nouse"], "name": "intonation", "children": [{"taxonID": "1-1-1", "level": "1", "path": "manner_$_of_$_speaking/prosody/intonation/intonation_$_pattern", "keywords": ["nouse"], "name": "intonation_$_pattern"}, {"taxonID": "1-1-1", "level": "1", "path": "manner_$_of_$_speaking/prosody/intonation/monotone", "keywords": ["nouse"], "name": "monotone"}, {"taxonID": "1-1-1", "level": "1", "path": "manner_$_of_$_speaking/prosody/intonation/singsong", "keywords": ["nouse"], "name": "singsong"}]}, {"taxonID": "1-1-1", "level": "1", "path": "manner_$_of_$_speaking/prosody/caesura", "keywords": ["nouse"], "name": "caesura"}, {"taxonID": "1-1-1", "level": "1", "path": "manner_$_of_$_speaking/prosody/rhythm", "keywords": ["nouse"], "name": "rhythm"}, {"taxonID": "1-1-1", "level": "1", "path": "manner_$_of_$_speaking/prosody/enjambment", "keywords": ["nouse"], "name": "enjambment"}]}, {"taxonID": "1-1-1", "level": "1", "path": "manner_$_of_$_speaking/tone", "keywords": ["nouse"], "name": "tone", "children": [{"taxonID": "1-1-1", "level": "1", "path": "manner_$_of_$_speaking/tone/undertone", "keywords": ["nouse"], "name": "undertone"}, {"taxonID": "1-1-1", "level": "1", "path": "manner_$_of_$_speaking/tone/roundness", "keywords": ["nouse"], "name": "roundness"}, {"taxonID": "1-1-1", "level": "1", "path": "manner_$_of_$_speaking/tone/note", "keywords": ["nouse"], "name": "note"}]}, {"taxonID": "1-1-1", "level": "1", "path": "manner_$_of_$_speaking/shibboleth", "keywords": ["nouse"], "name": "shibboleth"}, {"taxonID": "1-1-1", "level": "1", "path": "manner_$_of_$_speaking/address", "keywords": ["nouse"], "name": "address"}, {"taxonID": "1-1-1", "level": "1", "path": "manner_$_of_$_speaking/elocution", "keywords": ["nouse"], "name": "elocution"}, {"taxonID": "1-1-1", "level": "1", "path": "manner_$_of_$_speaking/catch", "keywords": ["nouse"], "name": "catch"}, {"taxonID": "1-1-1", "level": "1", "path": "manner_$_of_$_speaking/tongue", "keywords": ["nouse"], "name": "tongue", "children": [{"taxonID": "1-1-1", "level": "1", "path": "manner_$_of_$_speaking/tongue/sharp_$_tongue", "keywords": ["nouse"], "name": "sharp_$_tongue"}]}, {"taxonID": "1-1-1", "level": "1", "path": "manner_$_of_$_speaking/modulation", "keywords": ["nouse"], "name": "modulation"}]}]}